{
  "uptime": "1m2s",
  "packets_sent": 4,
  "packets_received": 5,
  "acks_sent": 3,
  "acks_received": 3,
  "checksums_failed": 0,
  "retransmissions": 1,
  "packets_lost": 0,
  "duplicates_received": 0,
  "out_of_order_received": 0,
  "bytes_sent": 113,
  "bytes_received": 116,
  "avg_rtt": "1.000557s",
  "min_rtt": "1.000382s",
  "max_rtt": "1.000673s",
  "packet_loss_rate_percent": 0,
  "retransmission_rate_percent": 25,
  "duplicate_rate_percent": 0,
  "throughput_sent_bps": 1.8194544012375784,
  "throughput_recv_bps": 1.8677585003854786,
  "packet_types_sent": {
    "MSG_REPORT": 3,
    "MSG_REQUEST": 1
  },
  "packet_types_received": {
    "MSG_ACK": 2,
    "MSG_MISSION": 3
  }
}